README.md
setup.py
fortimailapi/__init__.py
fortimailapi/fortimailapi.py
fortimailapi.egg-info/PKG-INFO
fortimailapi.egg-info/SOURCES.txt
fortimailapi.egg-info/dependency_links.txt
fortimailapi.egg-info/requires.txt
fortimailapi.egg-info/top_level.txt