Metadata-Version: 1.1
Name: fortimailapi
Version: 0.1.0
Summary: Python modules to interact with FortiMail product from Fortinet using REST API
Home-page: https://github.com/fortinet-solutions-cse/fortimailapi
Author: Miguel Angel Munoz Gonzalez
Author-email: magonzalez@fortinet.com
License: UNKNOWN
Keywords: Fortinet fortimail rest api
Platform: UNKNOWN
Classifier: Development Status :: 4 - Beta
Classifier: License :: OSI Approved :: Apache Software License
Classifier: Programming Language :: Python 
Classifier: Topic :: Security
